MANIFEST.in
Pipfile.lock
setup.py
ccvs_api_client.egg-info/PKG-INFO
ccvs_api_client.egg-info/SOURCES.txt
ccvs_api_client.egg-info/dependency_links.txt
ccvs_api_client.egg-info/entry_points.txt
ccvs_api_client.egg-info/requires.txt
ccvs_api_client.egg-info/top_level.txt
ccvs_scanning_api_client/__init__.py
ccvs_scanning_api_client/api_client.py
ccvs_scanning_api_client/configuration.py
ccvs_scanning_api_client/exceptions.py
ccvs_scanning_api_client/api/__init__.py
ccvs_scanning_api_client/api/analysis_api.py
ccvs_scanning_api_client/api/vendors_api.py
ccvs_scanning_api_client/command/__init__.py
ccvs_scanning_api_client/command/analysis.py
ccvs_scanning_api_client/command/run.py
ccvs_scanning_api_client/models/__init__.py
ccvs_scanning_api_client/models/analysis.py
ccvs_scanning_api_client/models/vendor.py
tests/__init__.py
tests/analysis_api_test.py
tests/api_client_test.py
tests/vendors_test.py