Metadata-Version: 1.0
Name: ccvs-api-client
Version: 1.2.0.1
Summary: CCVS API Client
Home-page: https://github.com/William-Hill-Online/CCVS-API-Client
Author: Ederson Brilhante
Author-email: ederson.brilhante@grandparade.co.uk
License: UNKNOWN
Keywords: CCVS API
Platform: UNKNOWN
